mylinky/__init__.py
mylinky/config.py
mylinky/entrypoint.py
mylinky/datedelta/__init__.py
mylinky/datedelta/datedelta.py
mylinky/enedis/__init__.py
mylinky/enedis/data.py
mylinky/enedis/enedis.py
mylinky/enedis/login.py
mylinky/exporter/__init__.py
mylinky/exporter/exporter.py
mylinky/exporter/influxdb/__init__.py
mylinky/exporter/influxdb/client.py
mylinky-0.15.dist-info/METADATA
mylinky-0.15.dist-info/WHEEL
mylinky-0.15.dist-info/entry_points.txt
mylinky-0.15.dist-info/top_level.txt
mylinky-0.15.dist-info/RECORD
