Metadata-Version: 2.1
Name: mylinky
Version: 0.15
Summary: Linky utility to grab your power consumption from ENEDIS
Home-page: https://github.com/x3n1x/linky
Author: Lionel Molinier
Author-email: lionel@molinier.eu
License: MIT
Platform: UNKNOWN
Requires-Dist: influxdb
Requires-Dist: requests-toolbelt
Requires-Dist: argparse
Requires-Dist: pyyaml
